[{"id":1,"username":"admin","email":"random@bing.com","parent":null,"name":null,"children":[{"id":2,"username":"test1","email":"adsad@asd.asd","parent":1,"name":"test1","children":[{"id":4,"username":"test3","email":"add@asd.asd","parent":2,"name":"test3","children":[{"id":5,"username":"test4","email":"addasd@asd.asd","parent":3,"name":"test4","children":[]}]}]},{"id":3,"username":"test2","email":"adsassd@asd.asd","parent":1,"name":"test2","podrizeni":[{"id":6,"username":"test5","email":"addasesd@asd.asd","parent":4,"name":"test5","children":[]}]}]}]
